README.md
setup.py
ocycle/__init__.py
ocycle/base.py
ocycle/baseio.py
ocycle/ocycle.py
ocycle/util.py
ocycle.egg-info/PKG-INFO
ocycle.egg-info/SOURCES.txt
ocycle.egg-info/dependency_links.txt
ocycle.egg-info/not-zip-safe
ocycle.egg-info/top_level.txt