Metadata-Version: 2.1
Name: ocycle
Version: 0.1.0
Summary: Stream buffering and event triggering for unbalanced frame sizes.
Home-page: https://github.com/beasteers/ocycle
Author: Bea Steers
Author-email: bea.steers@gmail.com
License: MIT License
Keywords: buffer callback io bytes bytesio unequal uneven frame size thread multiprocessing
Platform: UNKNOWN
